README.rst
setup.cfg
setup.py
testlinktests/__init__.py
testlinktests.egg-info/PKG-INFO
testlinktests.egg-info/SOURCES.txt
testlinktests.egg-info/dependency_links.txt
testlinktests.egg-info/requires.txt
testlinktests.egg-info/top_level.txt
testlinktests/configs/__init__.py
testlinktests/core/__init__.py
testlinktests/core/utils.py