Metadata-Version: 1.1
Name: testlinktests
Version: 0.0.0
Summary: Main automation lib to ensure behaviour of Testlink WebApp
Home-page: https://github.com/TestLinkOpenSourceTRMS/testlink-tests
Author: TestLinkOpenSourceTRMS
Author-email: netzuleando@gmail.com
License: NOTFOUND
Download-URL: https://github.com/TestLinkOpenSourceTRMS/testlink-tests/tarball/v0.0.0
Keywords: testing,logging,functional,http,test,testlink,XMLRPC,requests,webapp,selenium,functional
Platform: UNKNOWN
Classifier: Development Status :: 4 - Beta
Classifier: Intended Audience :: Developers
Classifier: Topic :: Software Development :: Build Tools
Classifier: Programming Language :: Python :: 2.7
Classifier: Programming Language :: Python :: 3.4
Classifier: Programming Language :: Python :: 3.5
Classifier: Programming Language :: Python :: 3.6
Classifier: License :: OSI Approved :: GNU General Public License v3 (GPLv3)
